{
  "sections": [
    {
      "type": "banner-slider",
      "autoplay": 9000,
      "full_width": false,
      "slides": [
        {
          "start": "",
          "end": "",
          "img": "/img/uploads/fitabf.webp",
          "link": "https://www.emporiotiasonia.com.br/pages/ofertas",
          "alt": "Black",
          "mobile_img": ""
        }
      ]
    },
    {
      "type": "document-banner",
      "enabled": true
    },
    {
      "type": "breadcrumbs",
      "enabled": true
    },
    {
      "type": "page-title"
    },
    {
      "type": "category-retail",
      "enabled": true,
      "sort": "sales"
    },
    {
      "type": "document-description",
      "enabled": true
    }
  ]
}