{
  "date": "2022-08-08T18:51:13.505Z",
  "title": "Alimentos que combatem a ansiedade: conheça quais são",
  "description": "Alimentação deve ser rica em magnésio, fibras, ômega-3, probióticos e triptofano",
  "body": "Você sabia que existem alimentos que combatem a ansiedade? \n\nEm resumo, uma alimentação rica em magnésio, fibras, ômega-3, probióticos e triptofano é ideal. Embora muitos pensem que a ansiedade deve ser tratada apenas com um psiquiatra ou psicólogo, a nutrição, também,  pode ser uma aliada fundamental. \n\nAfinal, cuidar do corpo reflete muito na saúde mental e, além de comer bem, é necessário conciliar com a prática de exercícios. Os sintomas da ansiedade podem ficar sob controle e o corpo fica ainda mais saudável.",
  "thumbnail": "/img/uploads/alimentos-que-combatem-a-ansiedade.jpg"
}